ubt_sphinx/__init__.py
ubt_sphinx/assets_manager.py
ubt_sphinx/builder.py
ubt_sphinx/exceptions.py
ubt_sphinx/git_collector.py
ubt_sphinx/minifier.py
ubt_sphinx/secure_ext.py
ubt_sphinx/ubt_types.py
ubt_sphinx/ubtrace.py
ubt_sphinx/search_assets/__init__.py
ubt_sphinx/search_assets/ubtrace_searchtools.js
ubt_sphinx/web_app/copy_db.py
ubt_sphinx-0.4.0.dist-info/licenses/LICENSE
ubt_sphinx-0.4.0.dist-info/WHEEL
ubt_sphinx-0.4.0.dist-info/METADATA
ubt_sphinx-0.4.0.dist-info/RECORD
