Metadata-Version: 2.1
Name: ubt-sphinx
Version: 0.4.0
Summary: Sphinx builder for ubTrace documentations.
Author-email: team useblocks <info@useblocks.com>
Maintainer-email: Marco Heinemann <marco.heinemann@useblocks.com>
Classifier: Development Status :: 3 - Alpha
Classifier: License :: Other/Proprietary License
Classifier: Operating System :: OS Independent
Classifier: Programming Language :: Python
Classifier: Topic :: Documentation
Requires-Python: ~=3.12
Requires-Dist: ubt_runtime
Requires-Dist: docutils~=0.20.1
Requires-Dist: sphinx>=5.0
Requires-Dist: sphinxcontrib-serializinghtml~=1.1.9
Requires-Dist: cssutils~=2.11.1
Requires-Dist: jsmin~=3.0.1
Requires-Dist: rcssmin~=1.1.3
Requires-Dist: sphinxcontrib-plantuml
Requires-Dist: tomlkit
